tests/__init__.py
tests/test_zomato.py
tests/modules/__init__.py
tests/modules/test_common.py
tests/modules/test_location.py
tests/modules/test_restaurant.py
tests/modules/utils.py
zomato/__init__.py
zomato/base.py
zomato/endpoint_manager.py
zomato/exceptions.py
zomato/requester.py
zomato/zomato.py
zomato/modules/__init__.py
zomato/modules/base_module.py
zomato/modules/Common/__init__.py
zomato/modules/Common/common.py
zomato/modules/Fundamentals/__init__.py
zomato/modules/Fundamentals/base_fundamental.py
zomato/modules/Fundamentals/categories.py
zomato/modules/Fundamentals/cities.py
zomato/modules/Fundamentals/collections.py
zomato/modules/Fundamentals/cuisines.py
zomato/modules/Fundamentals/daily_menu.py
zomato/modules/Fundamentals/establishments.py
zomato/modules/Fundamentals/geocode.py
zomato/modules/Fundamentals/location_details.py
zomato/modules/Fundamentals/location_suggestion.py
zomato/modules/Fundamentals/locations.py
zomato/modules/Fundamentals/restaurant_info.py
zomato/modules/Fundamentals/reviews.py
zomato/modules/Fundamentals/search.py
zomato/modules/Location/__init__.py
zomato/modules/Location/location.py
zomato/modules/Restaurant/__init__.py
zomato/modules/Restaurant/restaurant.py
zomato_sdk-0.1.0.dist-info/DESCRIPTION.rst
zomato_sdk-0.1.0.dist-info/METADATA
zomato_sdk-0.1.0.dist-info/RECORD
zomato_sdk-0.1.0.dist-info/WHEEL
zomato_sdk-0.1.0.dist-info/metadata.json
zomato_sdk-0.1.0.dist-info/top_level.txt
